sphinx_biel/__init__.py
sphinx_biel-0.1.8.dist-info/licenses/LICENSE.md
sphinx_biel-0.1.8.dist-info/WHEEL
sphinx_biel-0.1.8.dist-info/METADATA
sphinx_biel-0.1.8.dist-info/RECORD
