Metadata-Version: 2.4
Name: sphinx_biel
Version: 0.1.8
Summary: ASK AI chatbot for Sphinx.
Author-email: TechDocs Studio <info@techdocs.studio>
License-File: LICENSE.md
Project-URL: Home, https://github.com/TechDocsStudio/sphinx-biel
